bryte/__init__.py
bryte/__main__.py
bryte/config.txt
bryte/gene.py
bryte/processing.py
bryte/universal.py
bryte-0.1.3.dist-info/METADATA
bryte-0.1.3.dist-info/WHEEL
bryte-0.1.3.dist-info/entry_points.txt
bryte-0.1.3.dist-info/top_level.txt
bryte-0.1.3.dist-info/RECORD
