Metadata-Version: 2.1
Name: bryte
Version: 0.1.3
Summary: Python library of tools for enhancing your development, along with common shortcuts for speeding up your development
Home-page: https://github.com/mikeshobes718/Python-Packages/tree/master/bryte
Author: Mike Shobes
Author-email: mikeshobes718@yahoo.com
License: MIT
Platform: UNKNOWN
Classifier: Intended Audience :: Developers
Classifier: License :: OSI Approved :: MIT License
Classifier: Programming Language :: Python :: 2
Classifier: Programming Language :: Python :: 2.7
Classifier: Programming Language :: Python :: 3
Classifier: Programming Language :: Python :: 3.6
Classifier: Programming Language :: Python :: 3.7
Requires-Dist: os
Requires-Dist: sys
Requires-Dist: json
Requires-Dist: requests
Requires-Dist: subprocess
